verilog/contador/contador.srcs/sources_1/new/contador.v
`timescale 1ns / 1ps
//////////////////////////////////////////////////////////////////////////////////
// Company: 
// Engineer: 
// 
// Create Date: 31.07.2019 15:46:47
// Design Name: 
// Module Name: contador
// Project Name: 
// Target Devices: 
// Tool Versions: 
// Description: 
// 
// Dependencies: 
// 
// Revision:
// Revision 0.01 - File Created
// Additional Comments:
// 
//////////////////////////////////////////////////////////////////////////////////

module contador(input wire clk_in, output wire clk_out);
    
//-- Valor por defecto del divisor
//-- Como en la iCEstick el reloj es de 12MHz, ponermos un valor de 12M
//-- para obtener una frecuencia de salida de 1Hz
parameter M = 12_000_000;
    
//-- Numero de bits para almacenar el divisor
//-- Se calculan con la funcion de verilog $clog2, que nos devuelve el 
//-- numero de bits necesarios para representar el numero M
//-- Es un parametro local, que no se puede modificar al instanciar
localparam N = $clog2(M);
    
//-- Registro para implementar el contador modulo M
reg [N-1:0] divcounter = 0;
    
//-- Contador módulo M
always @(posedge clk_in)
  if (divcounter == M - 1) 
    divcounter <= 0;
  else 
    divcounter <= divcounter + 1;
    
//-- Sacar el bit mas significativo por clk_out
assign clk_out = divcounter[N-1];
    
endmodule

verilog/contador/contador.srcs/sim_1/new/contador_tb.v
`timescale 1ns / 1ps
//////////////////////////////////////////////////////////////////////////////////
// Company: 
// Engineer: 
// 
// Create Date: 31.07.2019 16:24:45
// Design Name: 
// Module Name: contador_tb
// Project Name: 
// Target Devices: 
// Tool Versions: 
// Description: 
// 
// Dependencies: 
// 
// Revision:
// Revision 0.01 - File Created
// Additional Comments:
// 
//////////////////////////////////////////////////////////////////////////////////

module contador_tb();
    
//-- Registro para generar la señal de reloj
reg clk = 0;
wire clk_out;
    
//-- Instanciar el componente y establecer el valor del divisor
contador #(8)
  dut(
    .clk_in(clk),
    .clk_out(clk_out)
  );
    
//-- Generador de reloj. Periodo 2 unidades
always #1 clk = ~clk;
    
//-- Proceso al inicio
initial begin
    
  //-- Fichero donde almacenar los resultados
  $dumpfile("contador_tb.vcd");
  $dumpvars(0, contador_tb);
    
  # 120 $display("FIN de la simulacion");
  $finish;
end
endmodule

verilog/contador/contador.sim/sim_1/behav/xsim/contador_tb.vcd
$date
   Wed Jul 31 18:38:30 2019
$end
$version
  2019.1
$end
$timescale
  1ps
$end
$scope module contador_tb $end
$var reg 1 ! clk $end
$var wire 1 " clk_out $end
$scope module dut $end
$var wire 1 # clk_in $end
$var wire 1 " clk_out $end
$var reg 3 $ divcounter [2:0] $end
$var parameter 32 % M [31:0] $end
$var parameter 32 & N [31:0] $end
$upscope $end
$upscope $end
$enddefinitions $end
#0
$dumpvars
0!
0"
0#
b0 $
b1000 %
b11 &
$end
#1000
1!
1#
b1 $
#2000
0!
0#
#3000
1!
1#
b10 $
#4000
0!
0#
#5000
1!
1#
b11 $
#6000
0!
0#
#7000
1!
1"
1#
b100 $
#8000
0!
0#
#9000
1!
1#
b101 $
#10000
0!
0#
#11000
1!
1#
b110 $
#12000
0!
0#
#13000
1!
1#
b111 $
#14000
0!
0#
#15000
1!
0"
1#
b0 $
#16000
0!
0#
#17000
1!
1#
b1 $
#18000
0!
0#
#19000
1!
1#
b10 $
#20000
0!
0#
#21000
1!
1#
b11 $
#22000
0!
0#
#23000
1!
1"
1#
b100 $
#24000
0!
0#
#25000
1!
1#
b101 $
#26000
0!
0#
#27000
1!
1#
b110 $
#28000
0!
0#
#29000
1!
1#
b111 $
#30000
0!
0#
#31000
1!
0"
1#
b0 $
#32000
0!
0#
#33000
1!
1#
b1 $
#34000
0!
0#
#35000
1!
1#
b10 $
#36000
0!
0#
#37000
1!
1#
b11 $
#38000
0!
0#
#39000
1!
1"
1#
b100 $
#40000
0!
0#
#41000
1!
1#
b101 $
#42000
0!
0#
#43000
1!
1#
b110 $
#44000
0!
0#
#45000
1!
1#
b111 $
#46000
0!
0#
#47000
1!
0"
1#
b0 $
#48000
0!
0#
#49000
1!
1#
b1 $
#50000
0!
0#
#51000
1!
1#
b10 $
#52000
0!
0#
#53000
1!
1#
b11 $
#54000
0!
0#
#55000
1!
1"
1#
b100 $
#56000
0!
0#
#57000
1!
1#
b101 $
#58000
0!
0#
#59000
1!
1#
b110 $
#60000
0!
0#
#61000
1!
1#
b111 $
#62000
0!
0#
#63000
1!
0"
1#
b0 $
#64000
0!
0#
#65000
1!
1#
b1 $
#66000
0!
0#
#67000
1!
1#
b10 $
#68000
0!
0#
#69000
1!
1#
b11 $
#70000
0!
0#
#71000
1!
1"
1#
b100 $
#72000
0!
0#
#73000
1!
1#
b101 $
#74000
0!
0#
#75000
1!
1#
b110 $
#76000
0!
0#
#77000
1!
1#
b111 $
#78000
0!
0#
#79000
1!
0"
1#
b0 $
#80000
0!
0#
#81000
1!
1#
b1 $
#82000
0!
0#
#83000
1!
1#
b10 $
#84000
0!
0#
#85000
1!
1#
b11 $
#86000
0!
0#
#87000
1!
1"
1#
b100 $
#88000
0!
0#
#89000
1!
1#
b101 $
#90000
0!
0#
#91000
1!
1#
b110 $
#92000
0!
0#
#93000
1!
1#
b111 $
#94000
0!
0#
#95000
1!
0"
1#
b0 $
#96000
0!
0#
#97000
1!
1#
b1 $
#98000
0!
0#
#99000
1!
1#
b10 $
#100000
0!
0#
#101000
1!
1#
b11 $
#102000
0!
0#
#103000
1!
1"
1#
b100 $
#104000
0!
0#
#105000
1!
1#
b101 $
#106000
0!
0#
#107000
1!
1#
b110 $
#108000
0!
0#
#109000
1!
1#
b111 $
#110000
0!
0#
#111000
1!
0"
1#
b0 $
#112000
0!
0#
#113000
1!
1#
b1 $
#114000
0!
0#
#115000
1!
1#
b10 $
#116000
0!
0#
#117000
1!
1#
b11 $
#118000
0!
0#
#119000
1!
1"
1#
b100 $
